ncbi_counts/__init__.py
ncbi_counts/__main__.py
ncbi_counts/__version__.py
ncbi_counts/core.py
ncbi_counts/load.py
ncbi_counts/parser.py
ncbi_counts/types.py
ncbi_counts/utils.py
ncbi_counts-0.2.0.dist-info/LICENSE
ncbi_counts-0.2.0.dist-info/METADATA
ncbi_counts-0.2.0.dist-info/WHEEL
ncbi_counts-0.2.0.dist-info/top_level.txt
ncbi_counts-0.2.0.dist-info/RECORD
