Metadata-Version: 2.1
Name: ncbi_counts
Version: 0.2.0
Summary: Download the NCBI-generated RNA-seq count data by specifying the Series accession number(s), and the regular expression of the Sample attributes.
Home-page: https://github.com/136s/ncbi_counts
Author: Yuki SUYAMA
License: MIT
Keywords: GEO,Gene Expression Omnibus,Bioinformatics,RNA-seq,NCBI
Classifier: Topic :: Scientific/Engineering :: Bio-Informatics
Classifier: License :: OSI Approved :: MIT License
Classifier: Programming Language :: Python
Classifier: Programming Language :: Python :: 3
Classifier: Programming Language :: Python :: 3 :: Only
Classifier: Programming Language :: Python :: 3.10
Classifier: Programming Language :: Python :: 3.11
Classifier: Programming Language :: Python :: 3.12
Classifier: Programming Language :: Python :: 3.13
Requires-Python: >=3.9.0
License-File: LICENSE
Requires-Dist: GEOparse
Requires-Dist: pandas
Requires-Dist: PyYAML
Provides-Extra: dev
Requires-Dist: pytest ; extra == 'dev'
Requires-Dist: build ; extra == 'dev'
Requires-Dist: twine ; extra == 'dev'
